mcp_studio/__init__.py
mcp_studio/version.py
mcp_studio-0.0.0.dist-info/LICENSE
mcp_studio-0.0.0.dist-info/METADATA
mcp_studio-0.0.0.dist-info/WHEEL
mcp_studio-0.0.0.dist-info/top_level.txt
mcp_studio-0.0.0.dist-info/RECORD
